urlmon/__init__.py
urlmon/urlmon.py
urlmon-0.1.1.dist-info/DESCRIPTION.rst
urlmon-0.1.1.dist-info/METADATA
urlmon-0.1.1.dist-info/RECORD
urlmon-0.1.1.dist-info/WHEEL
urlmon-0.1.1.dist-info/entry_points.txt
urlmon-0.1.1.dist-info/metadata.json
urlmon-0.1.1.dist-info/top_level.txt
