Metadata-Version: 2.0
Name: urlmon
Version: 0.1.1
Summary: Python script to monitor a webpage for changes.
Home-page: https://github.com/n8henrie/urlmon
Author: Nathan Henrie
Author-email: nate@n8henrie.com
License: MIT
Keywords: urlmon
Platform: UNKNOWN
Classifier: Natural Language :: English
Classifier: Programming Language :: Python :: 3
Classifier: Programming Language :: Python :: 3.3
Classifier: Programming Language :: Python :: 3.4
Classifier: Programming Language :: Python :: 3.5
Requires-Dist: beautifulsoup4 (==4.4.1)
Requires-Dist: keyring (==5.7.1)
Requires-Dist: pushover (==0.4)
Requires-Dist: py (==1.4.31)
Requires-Dist: pytest (==2.8.5)
Requires-Dist: requests (==2.9.1)
